disposable_email_domains/__init__.py
disposable_email_domains/py.typed
disposable_email_domains-0.0.155.dist-info/licenses/LICENSE.txt
disposable_email_domains-0.0.155.dist-info/METADATA
disposable_email_domains-0.0.155.dist-info/WHEEL
disposable_email_domains-0.0.155.dist-info/top_level.txt
disposable_email_domains-0.0.155.dist-info/RECORD
